textualeffects/__init__.py
textualeffects/effects.py
textualeffects/widgets.py
textualeffects-0.2.0.dist-info/METADATA
textualeffects-0.2.0.dist-info/WHEEL
textualeffects-0.2.0.dist-info/licenses/LICENSE
textualeffects-0.2.0.dist-info/RECORD
