Metadata-Version: 2.4
Name: textualeffects
Version: 0.2.0
Summary: Visual effects for Textual, a TermincalTextEffects wrapper.
Project-URL: Homepage, https://github.com/ggozad/textualeffects
Project-URL: Repository, https://github.com/ggozad/textualeffects
Project-URL: Issues, https://github.com/ggozad/textualeffects/issues
Author-email: Yiorgis Gozadinos <ggozadinos@gmail.com>
License: MIT
License-File: LICENSE
Classifier: Development Status :: 4 - Beta
Classifier: Environment :: Console
Classifier: Intended Audience :: Developers
Classifier: Operating System :: MacOS
Classifier: Operating System :: Microsoft :: Windows :: Windows 10
Classifier: Operating System :: Microsoft :: Windows :: Windows 11
Classifier: Operating System :: POSIX :: Linux
Classifier: Programming Language :: Python :: 3.10
Classifier: Programming Language :: Python :: 3.11
Classifier: Programming Language :: Python :: 3.12
Classifier: Typing :: Typed
Requires-Python: >=3.10
Requires-Dist: terminaltexteffects>=0.14.2
